tsv2dict.py
tsv2dict-0.0.3.dist-info/AUTHORS.rst
tsv2dict-0.0.3.dist-info/LICENSE
tsv2dict-0.0.3.dist-info/METADATA
tsv2dict-0.0.3.dist-info/WHEEL
tsv2dict-0.0.3.dist-info/entry_points.txt
tsv2dict-0.0.3.dist-info/top_level.txt
tsv2dict-0.0.3.dist-info/RECORD
