Metadata-Version: 2.1
Name: tsv2dict
Version: 0.0.3
Summary: Python support for linear TSV files
Home-page: https://github.com/nkurmann/tsv2dict
Author: Nico Kurmann
Author-email: nico.kurmann@gmail.com
License: MIT
Project-URL: Documentation, https://tsv2dict.readthedocs.io/
Project-URL: Changelog, https://tsv2dict.readthedocs.io/en/latest/changelog.html
Project-URL: Issue Tracker, https://github.com/nkurmann/tsv2dict/issues
Keywords: tsv,persistence,export
Platform: UNKNOWN
Classifier: Development Status :: 3 - Alpha
Classifier: Intended Audience :: Developers
Classifier: Intended Audience :: Science/Research
Classifier: License :: OSI Approved :: MIT License
Classifier: Operating System :: Unix
Classifier: Operating System :: POSIX
Classifier: Operating System :: Microsoft :: Windows
Classifier: Operating System :: OS Independent
Classifier: Programming Language :: Python
Classifier: Programming Language :: Python :: 3
Classifier: Programming Language :: Python :: 3 :: Only
Classifier: Programming Language :: Python :: 3.6
Classifier: Programming Language :: Python :: 3.7
Classifier: Programming Language :: Python :: 3.8
Classifier: Programming Language :: Python :: 3.9
Classifier: Programming Language :: Python :: Implementation :: CPython
Classifier: Programming Language :: Python :: Implementation :: PyPy
Classifier: Topic :: Utilities
Requires-Python: >=3.6
Provides-Extra: dev
Requires-Dist: autopep8 ; extra == 'dev'
Requires-Dist: binaryornot ; extra == 'dev'
Requires-Dist: check-manifest ; extra == 'dev'
Requires-Dist: click ; extra == 'dev'
Requires-Dist: flake8 ; extra == 'dev'
Requires-Dist: jinja2-time ; extra == 'dev'
Requires-Dist: mypy ; extra == 'dev'
Requires-Dist: pip-chill ; extra == 'dev'
Requires-Dist: poyo ; extra == 'dev'
Requires-Dist: pylint ; extra == 'dev'
Requires-Dist: pytest ; extra == 'dev'
Requires-Dist: python-slugify ; extra == 'dev'
Requires-Dist: tox ; extra == 'dev'
Requires-Dist: tsv2dict ; extra == 'dev'
Requires-Dist: twine ; extra == 'dev'
